nomnomdata/tools/engine/__init__.py
nomnomdata/tools/engine/cli.py
nomnomdata/tools/engine/code_sql_types.py
nomnomdata/tools/engine/create_new.py
nomnomdata/tools/engine/deploy.py
nomnomdata/tools/engine/docker_logging_utils.py
nomnomdata/tools/engine/model_update.py
nomnomdata/tools/engine/model_validator.py
nomnomdata/tools/engine/template/Dockerfile
nomnomdata/tools/engine/template/main.py
nomnomdata/tools/engine/template/pkg/__init__.py
nomnomdata/tools/engine/template/pkg/executable.py
nomnomdata/tools/engine/template/pkg/tests/__init__.py
nomnomdata/tools/engine/template/pkg/tests/test_executable.py
nomnomdata/tools/engine/template/requirements.txt
nomnomdata/tools/engine/testpass.out
nomnomdata/tools/engine/util.py
nomnomdata_tools_engine-2.0.10.dist-info/COPYING
nomnomdata_tools_engine-2.0.10.dist-info/COPYING.LESSER
nomnomdata_tools_engine-2.0.10.dist-info/LICENSE
nomnomdata_tools_engine-2.0.10.dist-info/METADATA
nomnomdata_tools_engine-2.0.10.dist-info/WHEEL
nomnomdata_tools_engine-2.0.10.dist-info/entry_points.txt
nomnomdata_tools_engine-2.0.10.dist-info/RECORD
