Metadata-Version: 2.1
Name: nomnomdata-tools-engine
Version: 2.0.10
Summary: Package containing tooling for developing nominode engines
Home-page: https://gitlab.com/nomnomdata/tools/nomnomdata-tools-engine
License: LGPL-3.0-only
Author: Nom Nom Data Inc
Author-email: info@nomnomdata.com
Requires-Python: >=3.9,<4.0
Classifier: License :: OSI Approved :: GNU Lesser General Public License v3 (LGPLv3)
Classifier: Programming Language :: Python :: 3
Classifier: Programming Language :: Python :: 3.9
Classifier: Programming Language :: Python :: 3.10
Classifier: Programming Language :: Python :: 3.11
Requires-Dist: aiobotocore[boto3] (>=2.15.2,<3.0.0)
Requires-Dist: cerberus (>=1.3.5,<2.0.0)
Requires-Dist: click-pathlib (>=2020.3.13,<2021.0.0)
Requires-Dist: docker[ssh] (>=7.1.0,<8.0.0)
Requires-Dist: dunamai (>=1.23.0,<2.0.0)
Requires-Dist: fsspec (>=2024.10.0,<2025.0.0)
Requires-Dist: jinja2 (>=3.1.4,<4.0.0)
Requires-Dist: nomnomdata-auth (>=3.0.1,<4.0.0)
Requires-Dist: pyyaml (>=6.0.2,<7.0.0)
Requires-Dist: requests (>=2.32.3,<3.0.0)
Requires-Dist: s3fs (>=2024.10.0,<2025.0.0)
Project-URL: Repository, https://gitlab.com/nomnomdata/tools/nomnomdata-tools-engine
